COPYRIGHT
MANIFEST.in
Makefile
README
mangler.py
setup.py
table.sql
tiddlywebconfig.py
test/__init__.py
test/__init__.pyc
test/test_compile.py
test/test_compile.pyc
test/test_simple.py
test/test_simple.pyc
tiddlywebplugins/__init__.py
tiddlywebplugins/mappingsql.py
tiddlywebplugins.mappingsql.egg-info/PKG-INFO
tiddlywebplugins.mappingsql.egg-info/SOURCES.txt
tiddlywebplugins.mappingsql.egg-info/dependency_links.txt
tiddlywebplugins.mappingsql.egg-info/namespace_packages.txt
tiddlywebplugins.mappingsql.egg-info/not-zip-safe
tiddlywebplugins.mappingsql.egg-info/requires.txt
tiddlywebplugins.mappingsql.egg-info/top_level.txt