Metadata-Version: 1.0
Name: tiddlywebplugins.mappingsql
Version: 1.1
Summary: Map a single RDBMS table to a bag.
Home-page: http://pypi.python.org/pypi/tiddlywebplugins.mappingsql
Author: Chris Dent
Author-email: cdent@peermore.com
License: UNKNOWN
Platform: Posix; MacOS X; Windows
